<DocInternals>
  <AlwaysLoose>
    <bool>false</bool>
    <bool>false</bool>
    <bool>false</bool>
    <bool>false</bool>
    <bool>false</bool>
  </AlwaysLoose>
  <FieldSrcTables>
    <String>6</String>
    <String>1</String>
    <String>X_ReloadTime</String>
    <String>7</String>
    <String>1</String>
    <String>X_ReloadTime</String>
    <String>8</String>
    <String>1</String>
    <String>Impresiones</String>
    <String>9</String>
    <String>1</String>
    <String>Impresiones</String>
    <String>10</String>
    <String>1</String>
    <String>Impresiones</String>
    <String>11</String>
    <String>1</String>
    <String>Impresiones</String>
    <String>12</String>
    <String>1</String>
    <String>Impresiones</String>
    <String>13</String>
    <String>1</String>
    <String>Impresiones</String>
    <String>14</String>
    <String>1</String>
    <String>Impresiones</String>
    <String>15</String>
    <String>1</String>
    <String>Impresiones</String>
    <String>16</String>
    <String>1</String>
    <String>Impresiones</String>
    <String>17</String>
    <String>1</String>
    <String>Impresiones</String>
    <String>18</String>
    <String>1</String>
    <String>Impresiones</String>
  </FieldSrcTables>
  <TableViewData>
    <Pos></Pos>
    <CtlInfo>
      <InternalView>
        <Tables>
          <TableViewTableWinSaveInfo>
            <Pos>
              <Left>387</Left>
              <Top>201</Top>
              <Width>153</Width>
              <Height>226</Height>
            </Pos>
            <Caption>Impresiones</Caption>
          </TableViewTableWinSaveInfo>
          <TableViewTableWinSaveInfo>
            <Pos>
              <Left>880</Left>
              <Top>332</Top>
              <Width>100</Width>
              <Height>64</Height>
            </Pos>
            <Caption>X_ReloadTime</Caption>
          </TableViewTableWinSaveInfo>
          <TableViewTableWinSaveInfo>
            <Pos>
              <Left>903</Left>
              <Top>291</Top>
              <Width>100</Width>
              <Height>46</Height>
            </Pos>
            <Caption>tExecTime</Caption>
          </TableViewTableWinSaveInfo>
          <TableViewTableWinSaveInfo>
            <Pos>
              <Left>409</Left>
              <Top>210</Top>
              <Width>100</Width>
              <Height>208</Height>
            </Pos>
            <Caption>Sheet1$</Caption>
          </TableViewTableWinSaveInfo>
          <TableViewTableWinSaveInfo>
            <Pos>
              <Left>624</Left>
              <Top>83</Top>
              <Width>100</Width>
              <Height>100</Height>
            </Pos>
            <Caption>Usr</Caption>
          </TableViewTableWinSaveInfo>
          <TableViewTableWinSaveInfo>
            <Pos>
              <Left>314</Left>
              <Top>268</Top>
              <Width>100</Width>
              <Height>100</Height>
            </Pos>
            <Caption>Usr-1</Caption>
          </TableViewTableWinSaveInfo>
          <TableViewTableWinSaveInfo>
            <Pos>
              <Left>279</Left>
              <Top>88</Top>
              <Width>100</Width>
              <Height>82</Height>
            </Pos>
            <Caption>$Syn 1 Table</Caption>
          </TableViewTableWinSaveInfo>
          <TableViewTableWinSaveInfo>
            <Pos>
              <Left>202</Left>
              <Top>204</Top>
              <Width>142</Width>
              <Height>100</Height>
            </Pos>
            <Caption>Impresiones-1</Caption>
          </TableViewTableWinSaveInfo>
          <TableViewTableWinSaveInfo>
            <Pos>
              <Left>222</Left>
              <Top>245</Top>
              <Width>100</Width>
              <Height>100</Height>
            </Pos>
            <Caption>IntervalMatch</Caption>
          </TableViewTableWinSaveInfo>
        </Tables>
        <BroomPoints></BroomPoints>
        <ConnectionPoints></ConnectionPoints>
        <ZoomFactor>3FF0000000000000</ZoomFactor>
      </InternalView>
      <SourceView></SourceView>
    </CtlInfo>
    <Mode>0</Mode>
  </TableViewData>
  <Bookmarks></Bookmarks>
  <SavedByVersion>11.20.12235.0409</SavedByVersion>
  <ForceBackEndMacroExecution>false</ForceBackEndMacroExecution>
  <FieldTags>
    <ScriptBased>
      <FieldTagData>
        <Tag>$key</Tag>
        <FieldNames>
          <String>$Field</String>
          <String>$Table</String>
        </FieldNames>
      </FieldTagData>
      <FieldTagData>
        <Tag>$hidden</Tag>
        <FieldNames>
          <String>$Field</String>
          <String>$Table</String>
          <String>$Rows</String>
          <String>$Fields</String>
          <String>$FieldNo</String>
          <String>$Info</String>
        </FieldNames>
      </FieldTagData>
      <FieldTagData>
        <Tag>$system</Tag>
        <FieldNames>
          <String>$Field</String>
          <String>$Table</String>
          <String>$Rows</String>
          <String>$Fields</String>
          <String>$FieldNo</String>
          <String>$Info</String>
        </FieldNames>
      </FieldTagData>
      <FieldTagData>
        <Tag>$ascii</Tag>
        <FieldNames>
          <String>$Field</String>
          <String>$Table</String>
          <String>$Info</String>
          <String>ReloadUser</String>
          <String>Maquina</String>
        </FieldNames>
      </FieldTagData>
      <FieldTagData>
        <Tag>$text</Tag>
        <FieldNames>
          <String>$Field</String>
          <String>$Table</String>
          <String>$Info</String>
          <String>ReloadUser</String>
          <String>Maquina</String>
          <String>User</String>
        </FieldNames>
      </FieldTagData>
      <FieldTagData>
        <Tag>$numeric</Tag>
        <FieldNames>
          <String>$Rows</String>
          <String>$Fields</String>
          <String>$FieldNo</String>
          <String>StartTime</String>
          <String>Total Jobs</String>
          <String>Color</String>
          <String>Mono</String>
          <String>Sheets</String>
          <String>Total Pages</String>
          <String>Job Cost</String>
          <String>N</String>
          <String>X</String>
          <String>Y</String>
        </FieldNames>
      </FieldTagData>
      <FieldTagData>
        <Tag>$integer</Tag>
        <FieldNames>
          <String>$Rows</String>
          <String>$Fields</String>
          <String>$FieldNo</String>
          <String>Total Jobs</String>
          <String>Color</String>
          <String>Mono</String>
          <String>Sheets</String>
          <String>Total Pages</String>
          <String>N</String>
          <String>X</String>
          <String>Y</String>
        </FieldNames>
      </FieldTagData>
      <FieldTagData>
        <Tag>$timestamp</Tag>
        <FieldNames>
          <String>StartTime</String>
        </FieldNames>
      </FieldTagData>
    </ScriptBased>
    <Interactive></Interactive>
  </FieldTags>
  <FieldComments></FieldComments>
  <TableComments></TableComments>
  <CreatePrjFolder>false</CreatePrjFolder>
  <LinkedTables></LinkedTables>
</DocInternals>
